<Signature xmlns="http://www.w3.org/2000/09/xmldsig#" Id="DistributorSignature">
<SignedInfo>
<CanonicalizationMethod Algorithm="http://www.w3.org/2001/10/xml-exc-c14n#"></CanonicalizationMethod>
<SignatureMethod Algorithm="http://www.w3.org/2001/04/xmldsig-more#rsa-sha512"></SignatureMethod>
<Reference URI=".gitignore">
<DigestMethod Algorithm="http://www.w3.org/2001/04/xmlenc#sha512"></DigestMethod>
<DigestValue>G5a6LTjvZMxejzWDlbmsHDNYOwpJ5bLyd66HtK3Iv/W7Q1liCpGwKkgUvgFAEo0yqQPqMDGylKKx
MXMQOxqmzw==</DigestValue>
</Reference>
<Reference URI=".sign.7z">
<DigestMethod Algorithm="http://www.w3.org/2001/04/xmlenc#sha512"></DigestMethod>
<DigestValue>NZ3ShFL9fMjsAcz9SytOD6QzmdlIHaOLsaYt0V6m6y3ljfkSHbnIxeFX/nehIG9vrw6vqiTLBAYK
Y7GWDWdmfQ==</DigestValue>
</Reference>
<Reference URI="LICENSE.APLv2">
<DigestMethod Algorithm="http://www.w3.org/2001/04/xmlenc#sha512"></DigestMethod>
<DigestValue>mPa3m3ePewoVQVvXUMOooJfWUFEctOyBFRiOEVxHBT/nAPV4iVwJcFHJvD37YZfCsToV3iAyc+Gj
IYiE+G6Q6A==</DigestValue>
</Reference>
<Reference URI="NOTICE">
<DigestMethod Algorithm="http://www.w3.org/2001/04/xmlenc#sha512"></DigestMethod>
<DigestValue>PKJ6amrlawESpHPaQtps/BYuGeC3Uhkc84vog9melXb1Vqca76AFokwlnkYACLPbn6lO0MsYKU6D
RNcfCoyBfg==</DigestValue>
</Reference>
<Reference URI="app%2Fapp.js">
<DigestMethod Algorithm="http://www.w3.org/2001/04/xmlenc#sha512"></DigestMethod>
<DigestValue>VAE8GyVGEyMjsc5H6bVZETjNfjKCrFySXe0pQ01+G0ZYn3rMvBghWcASYyifw6VUDDMcJ9TuApa4
vJLVIdNU6Q==</DigestValue>
</Reference>
<Reference URI="app%2Fcore%2F.gitignore">
<DigestMethod Algorithm="http://www.w3.org/2001/04/xmlenc#sha512"></DigestMethod>
<DigestValue>qxanDT+4AhE2N7vt3zco4LmdclvnsiZzylX72YHVSg+OTNYTqqAr6BELjG/+Jn0GX6S0duWVv8BT
3nyWmRfwCA==</DigestValue>
</Reference>
<Reference URI="app%2Fcore%2F.jscsrc">
<DigestMethod Algorithm="http://www.w3.org/2001/04/xmlenc#sha512"></DigestMethod>
<DigestValue>PFsleygtmY8QgXz5oUOUJYWMDQRtaJ9UGuVMsyAPDo5dkPM2HkOBQelxPnRYZfwNJ5xH+cvyBIfv
anC33KZZbg==</DigestValue>
</Reference>
<Reference URI="app%2Fcore%2F.jshintignore">
<DigestMethod Algorithm="http://www.w3.org/2001/04/xmlenc#sha512"></DigestMethod>
<DigestValue>2EKhca/UrNpsepkj6Uwov3XMMbJPYJz8E+GXKYLSjemVoSlSXHtPOqcRGscotAfXAOCwx0RL/5ze
pT5peXTTvQ==</DigestValue>
</Reference>
<Reference URI="app%2Fcore%2F.jshintrc">
<DigestMethod Algorithm="http://www.w3.org/2001/04/xmlenc#sha512"></DigestMethod>
<DigestValue>9p4JaBj8NSYy8mv2j6OE8xp0kEqVlP5mFJ0p3iYyMp6flKq/KYORfXZqEOlXRoW5uudH2Onz8Cam
3CyCvrP84Q==</DigestValue>
</Reference>
<Reference URI="app%2Fcore%2FREADME.md">
<DigestMethod Algorithm="http://www.w3.org/2001/04/xmlenc#sha512"></DigestMethod>
<DigestValue>pya70NcD+lCJbUQW767BpJBCUXnta1nYT98u1mBaTeAD2am70LHbekxwrpjagWog3n7PQKPvHmKW
tJpHf5QFSA==</DigestValue>
</Reference>
<Reference URI="app%2Fcore%2Fcore.js">
<DigestMethod Algorithm="http://www.w3.org/2001/04/xmlenc#sha512"></DigestMethod>
<DigestValue>lhj45NEX+7FmIvh1ZjTLmOxNbSCdd7f5WJ00HzCfZoyS5UBXNbOagwCe6Tyyo0RzJXFLbvkezJTw
Gpg/yUkz1w==</DigestValue>
</Reference>
<Reference URI="app%2Fcore%2Fcore%2Fapplication.js">
<DigestMethod Algorithm="http://www.w3.org/2001/04/xmlenc#sha512"></DigestMethod>
<DigestValue>rqoWH61m5qNbsPGdhEkGy6OaDh1JaeXkTrfDptJlvGQAC5kx96b5bnTo4lN0s5UmXWLL/A9XioE9
FKLO9MJt/w==</DigestValue>
</Reference>
<Reference URI="app%2Fcore%2Fcore%2Fevent.js">
<DigestMethod Algorithm="http://www.w3.org/2001/04/xmlenc#sha512"></DigestMethod>
<DigestValue>b3S/l1k9GrCTCicQ+egKXFk6m+WeAGznvUpYQHojNPTJ0vFiCXdizt2I5L5QpQf9T4hnnhkvFmF5
iSVfD9xsdg==</DigestValue>
</Reference>
<Reference URI="app%2Fcore%2Fcore%2Fstorage%2Fidb.js">
<DigestMethod Algorithm="http://www.w3.org/2001/04/xmlenc#sha512"></DigestMethod>
<DigestValue>scTEuIcqTWWOeQ8udzRWqlhQZzCTyBB4zbHbURCGkWzC4RFtNM/6stj+H2YodDSXobo4l86muaP4
V1SLxwGBUw==</DigestValue>
</Reference>
<Reference URI="app%2Fcore%2Fcore%2Fsysteminfo.js">
<DigestMethod Algorithm="http://www.w3.org/2001/04/xmlenc#sha512"></DigestMethod>
<DigestValue>aA4BJa/V5u5mcEC/xA1k9iI9oHt+DkXXSB5G4xpLuAMZmbmPrE0xZCcTEyhQ8bQ0ZhdKVr48RaZ2
ABz4nYzKPg==</DigestValue>
</Reference>
<Reference URI="app%2Fcore%2Fcore%2Ftizen.js">
<DigestMethod Algorithm="http://www.w3.org/2001/04/xmlenc#sha512"></DigestMethod>
<DigestValue>GeIEGzOHJ10F3c3hR20cr4hJmxwyMmArMg4bsBvXL6L09FVNAKuom3pBGUYn43BdAGC7+lBbJ4Y1
63RPOa1AVQ==</DigestValue>
</Reference>
<Reference URI="app%2Fcore%2Fcore%2Fwindow.js">
<DigestMethod Algorithm="http://www.w3.org/2001/04/xmlenc#sha512"></DigestMethod>
<DigestValue>Yg0TvtWaiXAtHHKgLcKbf18X7iMr/ZjDWPVfaR8hwQFNoKowy52B4tPBp72o1b4dhPt1OzXQdH+L
1xwKdpFL2w==</DigestValue>
</Reference>
<Reference URI="app%2Fhelpers%2Fdate.js">
<DigestMethod Algorithm="http://www.w3.org/2001/04/xmlenc#sha512"></DigestMethod>
<DigestValue>fdEseMEEZwwnNGr6ZCEpUaijoUdaYok/86+zcrkFknERoRVkn6zMt0DQh4/TVKOM9h0nrsLHX407
VYL986PZbQ==</DigestValue>
</Reference>
<Reference URI="app%2Fhelpers%2Fshape.js">
<DigestMethod Algorithm="http://www.w3.org/2001/04/xmlenc#sha512"></DigestMethod>
<DigestValue>Z5GzO+8UT7CqhmLz8ZpiGalRsOZyCZx4LDr9XjNoflCgGE+EQeGjB1pYktpxMndgsTcMDjfDgxE5
hUx1JHzUoQ==</DigestValue>
</Reference>
<Reference URI="app%2Fhelpers%2Ftext.js">
<DigestMethod Algorithm="http://www.w3.org/2001/04/xmlenc#sha512"></DigestMethod>
<DigestValue>7Su2DjBUPZ5ORMOTCSnaPJPIRyMZyIuKGhKcTVkH/MDH2H+iUmFpVE8T4MRhd/aOX3Ky+ilc+S4q
uoowPhkRgQ==</DigestValue>
</Reference>
<Reference URI="app%2Fmodels%2Fcalendar.js">
<DigestMethod Algorithm="http://www.w3.org/2001/04/xmlenc#sha512"></DigestMethod>
<DigestValue>lBZates39f2W6QuGdg6iVnT+VQ3sCjHpQwEJB9wwUv2ydANhFwvm7a0GdppOSC1bxTQl2bbHbw8n
2cRzMlRZ7g==</DigestValue>
</Reference>
<Reference URI="app%2Fmodels%2Fcalories.js">
<DigestMethod Algorithm="http://www.w3.org/2001/04/xmlenc#sha512"></DigestMethod>
<DigestValue>z4PhNX7vuL3xVChQ1m2AB9Yg5AULVxXcg/SpIdNs6c5H0NE8XYXysP+DGNKHfuwvY7kxvUdBeoGl
ODJ6+SfaPg==</DigestValue>
</Reference>
<Reference URI="app%2Fmodels%2FcanvasDrawer.js">
<DigestMethod Algorithm="http://www.w3.org/2001/04/xmlenc#sha512"></DigestMethod>
<DigestValue>oAgnGZ0TMYSngLd0OfVpbbrRkU7lUaObWLRbzWIjLHRvcC+n3xnniMmLcqw+KyzaTulyaTc8sRgS
qowwTnHzVA==</DigestValue>
</Reference>
<Reference URI="app%2Fmodels%2FheartRate.js">
<DigestMethod Algorithm="http://www.w3.org/2001/04/xmlenc#sha512"></DigestMethod>
<DigestValue>9/yQAodfUrAJ3FryRlsRWEoTSMHa00hvH707wNx02XHEW5VANYD7sWphj3daXf2j+Qk0QXnKvpFe
xW5lCxp9Mg==</DigestValue>
</Reference>
<Reference URI="app%2Fmodels%2Flocation.js">
<DigestMethod Algorithm="http://www.w3.org/2001/04/xmlenc#sha512"></DigestMethod>
<DigestValue>zn4q4a4EFEaLxdZ/RlXGdzAql03MO/Q153O7cB7GTszJumKBVmuqPrwMj5i1WNamDvYPYOpeDU9p
FWaC/3Cr6A==</DigestValue>
</Reference>
<Reference URI="app%2Fmodels%2Fmotion.js">
<DigestMethod Algorithm="http://www.w3.org/2001/04/xmlenc#sha512"></DigestMethod>
<DigestValue>UqIrJUSi6YqyDO0rOnjl7vqymwv5R5qSGHnqJjOr234JORx93rqRGDtyEbnflXLDVPO/bRaMX7gk
ld7ZOGo6gQ==</DigestValue>
</Reference>
<Reference URI="app%2Fmodels%2Fpedometer.js">
<DigestMethod Algorithm="http://www.w3.org/2001/04/xmlenc#sha512"></DigestMethod>
<DigestValue>T4CY1mFe9LRHa+bWJup37PU6RGwzVJQv5BMy0vBOflx5p6WjibOfAtwjv0aB+tlnmTE135bMIh7Y
D8GMiXe+8Q==</DigestValue>
</Reference>
<Reference URI="app%2Fmodels%2Fpressure.js">
<DigestMethod Algorithm="http://www.w3.org/2001/04/xmlenc#sha512"></DigestMethod>
<DigestValue>kzNZ3I9w5nxbYR+Yk25R1Mctt4jY+fEnx3KtJxNDZa3MIu9ld0wHlLCz4XSRtycsoE4Z7ZbIvgIo
jY8iAn+XAA==</DigestValue>
</Reference>
<Reference URI="app%2Fmodels%2Fsettings.js">
<DigestMethod Algorithm="http://www.w3.org/2001/04/xmlenc#sha512"></DigestMethod>
<DigestValue>P+tyFb5tYTAfTIO6FrCXPvP4ejuGJveUnCo31NvL6SEupjIayIk6SL3xg6We5q/Svqw6KgkoyNbH
dcAN0ZyPQw==</DigestValue>
</Reference>
<Reference URI="app%2Fmodels%2Fweather.js">
<DigestMethod Algorithm="http://www.w3.org/2001/04/xmlenc#sha512"></DigestMethod>
<DigestValue>+fPfey8nytMiCQ4DbFgPIhIB/YgPoJCGyHEvGvfh29l/ArkvXmgWzxva5DJmsh1xXXqSnbZUWSxx
SKjw2fBHsA==</DigestValue>
</Reference>
<Reference URI="app%2Ftau-config.js">
<DigestMethod Algorithm="http://www.w3.org/2001/04/xmlenc#sha512"></DigestMethod>
<DigestValue>4uO/1Gq8a3/K23CMOEYjwuGm2wiKcxaToAFNBAwm4x4qZfKY9WXFuZMVHqowYbMzKBuIHRt/Gju+
7AAC7BcJIw==</DigestValue>
</Reference>
<Reference URI="app%2Fviews%2Fcanvas.js">
<DigestMethod Algorithm="http://www.w3.org/2001/04/xmlenc#sha512"></DigestMethod>
<DigestValue>3e2UNLNv9keOJMZ4IQ++mLI19818k94sweu3IwXkrkAGmnhqiOoZjXz8p6R3MLcMtcIwrELTdxVK
Yw1SV1sjrg==</DigestValue>
</Reference>
<Reference URI="app%2Fviews%2Finit.js">
<DigestMethod Algorithm="http://www.w3.org/2001/04/xmlenc#sha512"></DigestMethod>
<DigestValue>GZSVMLKvrvJSSguJ+N1Qa7z3iBBK8ojgF1wowCjbdRyUqF9cVRdCDkNMbG3WFoid/xVOHtIP+wQS
mhOrwoBqiw==</DigestValue>
</Reference>
<Reference URI="app%2Fviews%2Fmain.js">
<DigestMethod Algorithm="http://www.w3.org/2001/04/xmlenc#sha512"></DigestMethod>
<DigestValue>pnEyRPdlfEAnesc7+h+SyrH9i6bW8mv0lNZt7gdWSGcBIeEJatfI7waPK2F+mo49eehjNQlOmoD4
y/wjlHIRig==</DigestValue>
</Reference>
<Reference URI="app%2Fviews%2Fradial.js">
<DigestMethod Algorithm="http://www.w3.org/2001/04/xmlenc#sha512"></DigestMethod>
<DigestValue>oUIpEMsk360N89NB/2Gc92UXjQpulIg75SlgWSaHYcpUsw1tIct7BvGQEQEEfvzmLCSgEVbC3bSe
uYiD4/nYhg==</DigestValue>
</Reference>
<Reference URI="app%2Fviews%2Fsettings.js">
<DigestMethod Algorithm="http://www.w3.org/2001/04/xmlenc#sha512"></DigestMethod>
<DigestValue>XUV8CW/w9/hEE9OOcK3L9fmhyR06vmWb9NM+xKbEcuDoRw5YROTYra1KFKRWyTJ4oX8bcYeMx47L
6bOkCYCVGA==</DigestValue>
</Reference>
<Reference URI="author-signature.xml">
<DigestMethod Algorithm="http://www.w3.org/2001/04/xmlenc#sha512"></DigestMethod>
<DigestValue>UosYObpWvTl2mRXqd1V8w4VS6a4wSJaRYVLOnEXHTblNxRtz3wRp072Daqj/bkiHbD9kgsvOxUGo
T5fL3iwIbQ==</DigestValue>
</Reference>
<Reference URI="config.xml">
<DigestMethod Algorithm="http://www.w3.org/2001/04/xmlenc#sha512"></DigestMethod>
<DigestValue>W8kglSLHHYcuB9F/cYc8Yzkl0/YPtMcxdMyIEgyYbQqfHj6jpOT/GTIHOZ5RRQ/HxXB60FPC8NHT
MW0NMTN8BA==</DigestValue>
</Reference>
<Reference URI="css%2Faugmented.css">
<DigestMethod Algorithm="http://www.w3.org/2001/04/xmlenc#sha512"></DigestMethod>
<DigestValue>brYSSRl6XSqXawq7QOENWtXp/q8dDM0DYbtnu36omWm7eOP5MkGj7gTHsMUhrPMb79etdOw17OCm
rM68Mg4zOg==</DigestValue>
</Reference>
<Reference URI="css%2Fstyle.css">
<DigestMethod Algorithm="http://www.w3.org/2001/04/xmlenc#sha512"></DigestMethod>
<DigestValue>xPoMSp6TKkLROZxzHDTY9tv/iIPRtiRXpfsuIyS3PFS5J8VJGmAVBVYP6K5mIk7gyaVoYx3GWIkc
e1N/7b9Ggw==</DigestValue>
</Reference>
<Reference URI="data%2Fdefault_app.json">
<DigestMethod Algorithm="http://www.w3.org/2001/04/xmlenc#sha512"></DigestMethod>
<DigestValue>86lT+eL6y/2RKCV4YP8OkDtfuK7V5WAQeF5DzHc8xubypjmX8i5QJnSDPHSKSmYCihIJSm/VTenX
1yKxyEPmwQ==</DigestValue>
</Reference>
<Reference URI="data%2Ffonts%2FFutureNow.ttf">
<DigestMethod Algorithm="http://www.w3.org/2001/04/xmlenc#sha512"></DigestMethod>
<DigestValue>DDMeLXs3dgCipVEGS35Xqu1WWKTb0s88CSpflU18S+UBZZVwpKSQhJ9SzKYLg3hQIo4YaN+o8Ueh
YcJJknHOug==</DigestValue>
</Reference>
<Reference URI="data%2Ffonts%2FSyncopate.woff2">
<DigestMethod Algorithm="http://www.w3.org/2001/04/xmlenc#sha512"></DigestMethod>
<DigestValue>q7ll88z+iL/nUdK5zgZWTqDHAa9zh/Uosa2aTLzWvv+E8pN1jQ8mL/Nm6Evor1qzKRpLxDucXukA
YC15QQLjNQ==</DigestValue>
</Reference>
<Reference URI="data%2Ficons%2Fweather%2Fartill_clean_icons.otf">
<DigestMethod Algorithm="http://www.w3.org/2001/04/xmlenc#sha512"></DigestMethod>
<DigestValue>bKdOXi1HIZZyl6/6ggDCU6dg4uamn8NJOcRWGaUyCu9y68PoePMr8UbjvfFGm/v9H9fMGAPnn5BP
SYci0Nq12Q==</DigestValue>
</Reference>
<Reference URI="data%2Fmapping.json">
<DigestMethod Algorithm="http://www.w3.org/2001/04/xmlenc#sha512"></DigestMethod>
<DigestValue>j3qvnAYuLe04VoMRDsRq8VUuV19kOFdKV5UWcDp8CqntWACVj5pYv2QsMdSOVSEMi8P5Tose4mz8
gNel6TE+5w==</DigestValue>
</Reference>
<Reference URI="data%2Fradial.json">
<DigestMethod Algorithm="http://www.w3.org/2001/04/xmlenc#sha512"></DigestMethod>
<DigestValue>xvGEuqLFygbdRYTY3ox4yMeCa3PxOvUyZ46tT+2nBaYf6/VRjKcuyIR7t7chu44Jd1jaMEWinnPE
SmbhS+ICsA==</DigestValue>
</Reference>
<Reference URI="data%2Fthemes%2Fcustom.json">
<DigestMethod Algorithm="http://www.w3.org/2001/04/xmlenc#sha512"></DigestMethod>
<DigestValue>FvxUl1jic5M5rZPOazgNSgpw0sCu56kjOjxyqv9EbQEugrmW9e3M72BLMI1FFuSFrCeQaq4sMIex
ERgtZk9b3w==</DigestValue>
</Reference>
<Reference URI="data%2Fthemes%2Ffire.json">
<DigestMethod Algorithm="http://www.w3.org/2001/04/xmlenc#sha512"></DigestMethod>
<DigestValue>TPQiRwVKMsZEcyErmayxAV0MLlDlI4KrLMY+tWiAo6myzdKjfvzQrAriig+bK87726dw924Z8+kd
2gp449aHRw==</DigestValue>
</Reference>
<Reference URI="data%2Fthemes%2Fhisakura.json">
<DigestMethod Algorithm="http://www.w3.org/2001/04/xmlenc#sha512"></DigestMethod>
<DigestValue>Y19wC57kYUDpXFmMhfSOaJA+okYd4MgmdXhTubXGzod7u9i5jQIkA7pMoHgjkZ4tFYgAwb7y043u
0lz970kv7A==</DigestValue>
</Reference>
<Reference URI="data%2Fthemes%2Fice.json">
<DigestMethod Algorithm="http://www.w3.org/2001/04/xmlenc#sha512"></DigestMethod>
<DigestValue>jtfKwbXrKgzu9MR2FWYsHNsmc1Bn/yOitDQ2hDP3d+Q2KUHAZOrMiLj91Mc/3xDwSCyAAmqn1dKb
vpzkB/rl3Q==</DigestValue>
</Reference>
<Reference URI="data%2Fthemes%2Fmetal.json">
<DigestMethod Algorithm="http://www.w3.org/2001/04/xmlenc#sha512"></DigestMethod>
<DigestValue>vkKtm8pFFxqfMOV6FdhB9GsjEIY5fcYO/7LiBymY8N7H1P8ggAtUZMBe/P6TrHBxlQy8EEb3GqcT
ofVRvoy0+Q==</DigestValue>
</Reference>
<Reference URI="data%2Fweather.json">
<DigestMethod Algorithm="http://www.w3.org/2001/04/xmlenc#sha512"></DigestMethod>
<DigestValue>a/PehaTBLm3k2yZT8OSNJ+o0O3WgvJSbqirX5j2HCZlKh/kzyHhRS1vffZBsi5F399sYKf8XBpGs
QRPdPCzyZw==</DigestValue>
</Reference>
<Reference URI="data%2Fweather.xml">
<DigestMethod Algorithm="http://www.w3.org/2001/04/xmlenc#sha512"></DigestMethod>
<DigestValue>rIqeCq9DfSNG80THvGoMOMnClxcrmPcfGtGi1sB3TYOyU1uDVTTlHyuSJ6kLu1FR83/ofo3YfKDU
18fD3jnXJA==</DigestValue>
</Reference>
<Reference URI="data%2Fweather_forcast.json">
<DigestMethod Algorithm="http://www.w3.org/2001/04/xmlenc#sha512"></DigestMethod>
<DigestValue>adPHjjSzPKNx8VgfWnHxp3C8yVwkHVGnqoIDQRb0RxQ/TIWMW+zlhPa1ROwShUt1l6JaD1zWHk3U
VcWXr7yt2Q==</DigestValue>
</Reference>
<Reference URI="data%2Fweather_forcast.xml">
<DigestMethod Algorithm="http://www.w3.org/2001/04/xmlenc#sha512"></DigestMethod>
<DigestValue>iMclcIedplrA6NIXclEYrXwpI5ipGeUBnjtEz8Vv+UyLMpeGodWaBXRlH5wxqruYgVt6sd/vo69x
22nfXFBvRg==</DigestValue>
</Reference>
<Reference URI="icon.png">
<DigestMethod Algorithm="http://www.w3.org/2001/04/xmlenc#sha512"></DigestMethod>
<DigestValue>S+qz/K7QzpTQvADej6Nl3+cCM+7vz4Ya1hPEebznTIewchS3yvrGxUE1a69hdraDysg3UX1X9ov0
MA32z4k3gA==</DigestValue>
</Reference>
<Reference URI="images%2Ficon.jpg">
<DigestMethod Algorithm="http://www.w3.org/2001/04/xmlenc#sha512"></DigestMethod>
<DigestValue>klr6maLNqVQ2LI5DEWeeZ4n2eMDf8hr46UbQS8Tkm4Gx2mEuPU3LG7PW7h3V70CJdCBYxnJLNJHt
8ww8FsQtQw==</DigestValue>
</Reference>
<Reference URI="index.html">
<DigestMethod Algorithm="http://www.w3.org/2001/04/xmlenc#sha512"></DigestMethod>
<DigestValue>1T2wJTkkJePHA3NPs/LV7e3pTVwVfeD1ihfPaNWHQcaUw1y4KEEycCT3va2y0IfN2asrD5Qqy4uK
yv3x5gLldQ==</DigestValue>
</Reference>
<Reference URI="lib%2Fcalendar%2FDayEvents.class.js">
<DigestMethod Algorithm="http://www.w3.org/2001/04/xmlenc#sha512"></DigestMethod>
<DigestValue>SMJNGTHNxy//Rg3nAIPo4tN0nd9SjWxuXr8q8CIR8JOPhvg3iPBSKS0DoauccVCIk/JmisZDv3XO
nZ1Fj9nSlQ==</DigestValue>
</Reference>
<Reference URI="lib%2Fcalendar%2FvEvent.class.js">
<DigestMethod Algorithm="http://www.w3.org/2001/04/xmlenc#sha512"></DigestMethod>
<DigestValue>yqlud92htLzZQOsGWzVH6Ae0nPh7XDPrP5YFTVaSStUDNhDQPcBxr21EhhpXp4vxTexmG5xvObtw
s2eUwySb+Q==</DigestValue>
</Reference>
<Reference URI="lib%2Fdateadd.js">
<DigestMethod Algorithm="http://www.w3.org/2001/04/xmlenc#sha512"></DigestMethod>
<DigestValue>iMRvAPzxhpZLc601Oe7gWjayjZRSEYOLDs3JzcQCltKoZhLfrupGXamnOX2i+3dR9WM7FbzYvkx2
rJBADjAZbQ==</DigestValue>
</Reference>
<Reference URI="lib%2Feffects%2FAlien.class.js">
<DigestMethod Algorithm="http://www.w3.org/2001/04/xmlenc#sha512"></DigestMethod>
<DigestValue>iIdAeTCM80vwpUEtA7qU8w22Dy6OxwF8YYPQHPrTOO/hc9ydItJr30vFogkbmCIntDyWoWVE9v7V
CtUxeKFUCA==</DigestValue>
</Reference>
<Reference URI="lib%2Feffects%2FFlame.class.js">
<DigestMethod Algorithm="http://www.w3.org/2001/04/xmlenc#sha512"></DigestMethod>
<DigestValue>Uy+GIPVIG/hLlvRZ0Vi6lly8YnL72i/EanhbqukQYm1HVF+qucQ6KS3rAKQsLHk42DuW8nVyXpGY
RAtXjsnt7g==</DigestValue>
</Reference>
<Reference URI="lib%2Feffects%2FFlower.class.js">
<DigestMethod Algorithm="http://www.w3.org/2001/04/xmlenc#sha512"></DigestMethod>
<DigestValue>RV4qC9Of3DLrGG91JdSKvPIEAdY8jIn8VaNWq8O0/a9OFMLOwzock9P9Rq5TN7JitVhCi6nkSsFA
muQ/ic9Y9w==</DigestValue>
</Reference>
<Reference URI="lib%2Feffects%2FLightSpeed.class.js">
<DigestMethod Algorithm="http://www.w3.org/2001/04/xmlenc#sha512"></DigestMethod>
<DigestValue>++yOiQ8O6aQqlOHs2stP83/Gzz1VMaQi8ZiQDm5qoC2ho/4BUvvpBN26wE+mnItkS81KVIOiuEKg
wat/p3lalA==</DigestValue>
</Reference>
<Reference URI="lib%2Feffects%2FParticle.class.js">
<DigestMethod Algorithm="http://www.w3.org/2001/04/xmlenc#sha512"></DigestMethod>
<DigestValue>ss6VUgMW31JZO+YxUwRhny8yG9gr2YRqt4X9EF7UE5Y30gZtW4Plj3BFkW3EMy0E6jNGG4OPk7/t
r9Ne7bUT5A==</DigestValue>
</Reference>
<Reference URI="lib%2Feffects%2FParticleAlien.class.js">
<DigestMethod Algorithm="http://www.w3.org/2001/04/xmlenc#sha512"></DigestMethod>
<DigestValue>Mu2TVGpo+Tb6fhWAmr2Jt5bFPYmR95qhNl3ofJZ+0RGt3pei4m8dWtzQctiy6AkKDWf685L9KFKT
bPJlynw3Lg==</DigestValue>
</Reference>
<Reference URI="lib%2Feffects%2FParticleEngine.class.js">
<DigestMethod Algorithm="http://www.w3.org/2001/04/xmlenc#sha512"></DigestMethod>
<DigestValue>A+0qsSIurdcJnJqDsNzijrR2lJTZz/cSXHHWAIifuQkhLWNq4t4rJzs+Wmo9dXzbTkg146HXtWIr
0JhsTUnIGQ==</DigestValue>
</Reference>
<Reference URI="lib%2Fextra.js">
<DigestMethod Algorithm="http://www.w3.org/2001/04/xmlenc#sha512"></DigestMethod>
<DigestValue>zM1EnSQ/voBPqGZJUl8ximqX1FvifdjVXkkHFvChdqn2q6lYYIz5/Qv5q1zVIKiNG9Ir0GCko7T4
cTJXBoLa7w==</DigestValue>
</Reference>
<Reference URI="lib%2Fradial%2Fcss%2FRadialMenu.css">
<DigestMethod Algorithm="http://www.w3.org/2001/04/xmlenc#sha512"></DigestMethod>
<DigestValue>EFQu52g4iulHT8gVYcgA6WIkFXp7YT3vRzGycf6h5CclgU1Q0pDciBvTEdwBrNoXuss7jqiDx0/5
viM5J7L4bQ==</DigestValue>
</Reference>
<Reference URI="lib%2Fradial%2Fcss%2Fmain.css">
<DigestMethod Algorithm="http://www.w3.org/2001/04/xmlenc#sha512"></DigestMethod>
<DigestValue>/PP4VmzNXSMqOT52ErP9AgwpQr3g5EO8qeOMMpY6N60TUrSuTquSRIjGJE0Mng2n1O+//qdElii9
8p7wwiVSug==</DigestValue>
</Reference>
<Reference URI="lib%2Fradial%2Fjs%2FRadialMenu.js">
<DigestMethod Algorithm="http://www.w3.org/2001/04/xmlenc#sha512"></DigestMethod>
<DigestValue>XW2Dl5D9Eg/OgRh+A8YkRBBWUZvlWgXMUhoLgjeCeI7sDfgEnzP/gdDgUidS1hS7fR6ltVLlvWHD
aPyP3mUIsw==</DigestValue>
</Reference>
<Reference URI="lib%2Fshapes%2FCircle.class.js">
<DigestMethod Algorithm="http://www.w3.org/2001/04/xmlenc#sha512"></DigestMethod>
<DigestValue>Gr/1Ms3Zgn8WaDmc98aQsyFsDdGSZln4MRvSVreYuBaLAGyXxdNrVaDJ5OckbiFhEN+WBK9nXff9
PpvsEUOVcQ==</DigestValue>
</Reference>
<Reference URI="lib%2Fshapes%2FShape.class.js">
<DigestMethod Algorithm="http://www.w3.org/2001/04/xmlenc#sha512"></DigestMethod>
<DigestValue>zJNlawqnHnHSfaxViCV2l5SzC9XBVWSZ/7kjDJ8NmxYJdEjCAgS+TEHLGJeNDhQh/p4uo/RDiobr
4nt3zfEOfQ==</DigestValue>
</Reference>
<Reference URI="lib%2Futils%2FFetcher.class.js">
<DigestMethod Algorithm="http://www.w3.org/2001/04/xmlenc#sha512"></DigestMethod>
<DigestValue>uRgCssdjSeE/DLc1tYbwEO1myMD0uqeAAWyS8vP2tEJDDqjlOSk+aEE7WPEy3w4tMzDIVM4rwLSY
zS0Zkg/vJg==</DigestValue>
</Reference>
<Reference URI="lib%2Fweather%2FForecastDay.class.js">
<DigestMethod Algorithm="http://www.w3.org/2001/04/xmlenc#sha512"></DigestMethod>
<DigestValue>WNAf2ru72M0hsCovqWQ+wv4quUAXGIR29uhPBgdMiWQnI/1PKMR9ErkFywFf8F2K3F397gNVvaXZ
G5I1ihnPEw==</DigestValue>
</Reference>
<Reference URI="lib%2Fweather%2FvForecast.class.js">
<DigestMethod Algorithm="http://www.w3.org/2001/04/xmlenc#sha512"></DigestMethod>
<DigestValue>BMnzDxo1YH6dxXjkr+ki9CzWPXj9bIJ0L7t3Z1jDvnZPNqY0GkQ9PQflQQG/yNqu+hIArBOgCF9m
3O9KAPBgwQ==</DigestValue>
</Reference>
<Reference URI="lib%2Fworkers%2FcalendarWk.js">
<DigestMethod Algorithm="http://www.w3.org/2001/04/xmlenc#sha512"></DigestMethod>
<DigestValue>l9IyGhzdU3s/mZXg+q8sXEB2mRVagEIH2zFxi+GfY0vnk3SBZGurSZpxJfGixmtPPzDZbIhftm4F
b2PHQu2RUA==</DigestValue>
</Reference>
<Reference URI="lib%2Fworkers%2Ffetcher.class.js">
<DigestMethod Algorithm="http://www.w3.org/2001/04/xmlenc#sha512"></DigestMethod>
<DigestValue>4aygLiOFd16lWaAwGFlvBvE6hO5wopnGYPYNCDPdiU73AijtkLWE/J3I6Q+By3pcD7kXbqsPD5QJ
sxKGICLpoQ==</DigestValue>
</Reference>
<Reference URI="lib%2Fworkers%2FforecastWk.js">
<DigestMethod Algorithm="http://www.w3.org/2001/04/xmlenc#sha512"></DigestMethod>
<DigestValue>zgEnQhmw5cdPkucC/K7lLQ5ThtRIiX4iJ6RuZCxpVJfeG8bl2ND0k/8aMFArRQjAQabXx7QApTjg
Wz0ocxRCgA==</DigestValue>
</Reference>
<Reference URI="lib%2Fworkers%2FjSonReaderWK.js">
<DigestMethod Algorithm="http://www.w3.org/2001/04/xmlenc#sha512"></DigestMethod>
<DigestValue>Q/MiimthncyIxMnO4USAOV4YtVw7kXAVDzQQMXzuwWXY7sjnsP33MWdpE2iXc9AmOhdOTlBrY0ys
ZsPitfCEhw==</DigestValue>
</Reference>
<Reference URI="lib%2Fworkers%2FpopolateWk.js">
<DigestMethod Algorithm="http://www.w3.org/2001/04/xmlenc#sha512"></DigestMethod>
<DigestValue>z4PhNX7vuL3xVChQ1m2AB9Yg5AULVxXcg/SpIdNs6c5H0NE8XYXysP+DGNKHfuwvY7kxvUdBeoGl
ODJ6+SfaPg==</DigestValue>
</Reference>
<Reference URI="lib%2Fworkers%2FweatherWk.js">
<DigestMethod Algorithm="http://www.w3.org/2001/04/xmlenc#sha512"></DigestMethod>
<DigestValue>eTvYLmziREXiT9Vn00A7BT5K0UOmI+bUHZpksifrE8ycXsDJmioHEM+C+HTU6QQdZkQJQSLThfew
4e68sGkSLg==</DigestValue>
</Reference>
<Reference URI="locales%2Fen.json">
<DigestMethod Algorithm="http://www.w3.org/2001/04/xmlenc#sha512"></DigestMethod>
<DigestValue>4/LagV7uML32WR9A/p/ydZ9YprK7/cpIGUqQUzgQqkdWjrJIpN2db4mcWqHjKitECqrwL+VAAnkK
79RF4LUVgQ==</DigestValue>
</Reference>
<Reference URI="locales%2Ffr.json">
<DigestMethod Algorithm="http://www.w3.org/2001/04/xmlenc#sha512"></DigestMethod>
<DigestValue>Olncbe5man+l7ecOTlns9msYcUEQ2oTW00cWd3tsz39K4VaKGaXUw+5S4oSuDlXfXlpBULXfsqgI
cf+f91LigQ==</DigestValue>
</Reference>
<Reference URI="output.txt">
<DigestMethod Algorithm="http://www.w3.org/2001/04/xmlenc#sha512"></DigestMethod>
<DigestValue>z4PhNX7vuL3xVChQ1m2AB9Yg5AULVxXcg/SpIdNs6c5H0NE8XYXysP+DGNKHfuwvY7kxvUdBeoGl
ODJ6+SfaPg==</DigestValue>
</Reference>
<Reference URI="version.txt">
<DigestMethod Algorithm="http://www.w3.org/2001/04/xmlenc#sha512"></DigestMethod>
<DigestValue>jJtvGOhH+xRt5nb2nvtEt+HGe/PG0CnhcMjO6XKTjHZEjeAZ5yuYeNEv9jXlGeLwx2zOOKSyvcob
EviMmoUiyw==</DigestValue>
</Reference>
<Reference URI="#prop">
<Transforms>
<Transform Algorithm="http://www.w3.org/2006/12/xml-c14n11"></Transform>
</Transforms>
<DigestMethod Algorithm="http://www.w3.org/2001/04/xmlenc#sha512"></DigestMethod>
<DigestValue>/r5npk2VVA46QFJnejgONBEh4BWtjrtu9x/IFeLksjWyGmB/cMWKSJWQl7aU3YRQRZ3AesG8gF7q
GyvKX9Snig==</DigestValue>
</Reference>
</SignedInfo>
<SignatureValue>
kJNNjtHI/VQqBhwx3/tYnetcwwMrgh2I4JncMmMWvbhJyXe9U5YdhEcA+cQU1JRtzad6pC9d9xZ2
1xZBtvU/3IDkGhonEGDVDfsWVnt/YSWYTGJgvHt74AzQJTmo/kVHvejFn3TRI/JCGmSW/Z+hkk1d
MHd2+QMkx/a1pArDyXwpnqM2nCV1l5ml4xM0BVjbkcAQijQjC/WXkvS2bQGQTVybgG4DpcouIWv/
/hnQ6wHoNB6tj0xT0Y0n6/W3hJYbtDVuhhpMuxJPGhBhMNIUPMDJ/2MTDg9T4qwPDytlq1lyuNOD
bL1fzWILcHbGvKDXJ7nT2P2hhcCQja8q6tZNqA==
</SignatureValue>
<KeyInfo>
<X509Data>
<X509Certificate>
MIID5zCCAs+gAwIBAgIBZTANBgkqhkiG9w0BAQ0FADCBnjELMAkGA1UEBhMCS1IxFDASBgNVBAgM
C1NvdXRoIEtvcmVhMQ4wDAYDVQQHDAVTdXdvbjEmMCQGA1UECgwdU2Ftc3VuZyBFbGVjdHJvbmlj
cyBDby4sIEx0ZC4xDzANBgNVBAsMBk1vYmlsZTEwMC4GA1UEAwwnU2Ftc3VuZyBUaXplbiBERVZF
TE9QRVIgUHVibGljIENBIENsYXNzMB4XDTIwMDczMDIyMTE1N1oXDTIxMDczMDIyMTE1N1owdTER
MA8GA1UEAwwIVGl6ZW5TREsxCTAHBgNVBAsMADEJMAcGA1UECgwAMQkwBwYDVQQHDAAxCTAHBgNV
BAgMADEJMAcGA1UEBhMAMSkwJwYJKoZIhvcNAQkBFhp6b3J6ZXR0by5hbnRob255QGdtYWlsLmNv
bTCCASIwDQYJKoZIhvcNAQEBBQADggEPADCCAQoCggEBAKqTkO9Tu9QTStJwGmSvqQfziR9IuTZD
5vRyGNlc1THiZXgueoA0uc8qbbKy8ofyAGzDWeFIu/cJ+lP4nZVE9XyMXaajlEpmQ9lgTNEppOwC
nBi8e+VwGXX3R8hLutpZ8cyToVo2jsJH5BhXL1rKKeuNqP6TjbUzUJN161U2lwN45csXcdX/miF+
8orONadx2a+m90v2Zt4wpv5SD1UfP+R1LEHosnl21IrEOdCC0DJYXa/eSmKTvL5zLqT4akAzww+V
wiw51hJI2gSMAVJ8crF3vjNhUBnPOdQWiBrnuDacswx8j39OmROhalT9+8EAIG5te2Y51LcJRBc7
eKWUPVMCAwEAAaNYMFYwVAYDVR0RBE0wS4YUVVJOOnRpemVuOnBhY2thZ2VpZD2GM1VSTjp0aXpl
bjpkZXZpY2VpZD0yLjAjRGU0d2VYekxPMVgzd1Iyd2RJbmdDdVJrNCtnPTANBgkqhkiG9w0BAQ0F
AAOCAQEAe8c6sZ6Bxrlyw4yI5JNiJj3H3CaY56XGbXP+lkwakwW3NuxMnaYGU+m6A3RSsuYOMVLf
rlcEaX9mv7a9EcIHqFfYGXnm9jH4CrythtNOMWueCVN/KdlXVTFb+89X6XGRQhN2aihZ3b/raeT9
P/d40zS0sJQxxrOM/1kYCVyRK61/1xbg30zPzmR1rA0STfrNWU6Xo7sUpeUA4xBUkd6gPquCX65+
ijKcNOnx8Un1BjzznXLgyDQ5fbBwGTpo+jAhazD8h+PwVPD69aPUpzQgEseECkOg8sW1N8u3C7y4
i1DzQCKV4uU6AkPMMlpJgDJIT0EGAz29cnZWee6SEPgmHA==
</X509Certificate>
<X509Certificate>
MIIDuzCCAqOgAwIBAgICL+cwDQYJKoZIhvcNAQELBQAwgY8xCzAJBgNVBAYTAktSMRQwEgYDVQQI
DAtTb3V0aCBLb3JlYTEOMAwGA1UEBwwFU3V3b24xJjAkBgNVBAoMHVNhbXN1bmcgRWxlY3Ryb25p
Y3MgQ28uLCBMdGQuMTIwMAYDVQQDDClTYW1zdW5nIFRpemVuIERFVkVMT1BFUiBQdWJsaWMgUm9v
dCBDbGFzczAeFw0xMzEyMzAxNTAxNDdaFw0yODEyMjYxNTAxNDdaMIGeMQswCQYDVQQGEwJLUjEU
MBIGA1UECAwLU291dGggS29yZWExDjAMBgNVBAcMBVN1d29uMSYwJAYDVQQKDB1TYW1zdW5nIEVs
ZWN0cm9uaWNzIENvLiwgTHRkLjEPMA0GA1UECwwGTW9iaWxlMTAwLgYDVQQDDCdTYW1zdW5nIFRp
emVuIERFVkVMT1BFUiBQdWJsaWMgQ0EgQ2xhc3MwggEiMA0GCSqGSIb3DQEBAQUAA4IBDwAwggEK
AoIBAQCkqW9d0zO5NFOc7u164DKe9Yx+yEgUnsbhnJasqHaqT71qaMxyCOjyysZi7gGycDcgmLcU
tr2wSMTGWPibK8SrJ8bV/J1cy9nTpljM3s+lbPIVVxZeufhJkU79tXImHLolERd0vui+rj0Xpd9O
zlyNTRt0+PWVT1taWcbfHL7pUD25hMkTc8C3bC+dUoT1/RhCkXgmUvIor3EnnU0rBtAl4qNtg5y1
7RLT8dyicieAHCcW923YC/ngMZxnBjbL2Ht1RBUvrL6K3X5+l0VeF4qC3g7TKm/a/SGjq12ZD4sc
7rglzjSNlTVSGag6/2WkqxE6HheEBWaloYOdauzwydFNAgMBAAGjEDAOMAwGA1UdEwQFMAMBAf8w
DQYJKoZIhvcNAQELBQADggEBAG88wKjKeTbj5I6wMEvRihd+gWrESJX3bXUSlHWjUfYKcvg3GzM9
cdooscqJdYgN8ezQuYiJQRk7BaPHSlPGkchsPUjvSM6WvIn9IT+VsEuVBrZNbZMSv6lM6wNig3TE
h2OxFTW6Bt8mCZB74EP2wb+39Fr5aJwWvmkxQjct3/O+GYPQhe0Lu1qpbbMhzafYYybSmO+om02V
cTWyJ/vtLUNyGfN7aHyBm6PFE5piAfpBaO9Az+zWil1HOsnzu1tGGnyV6IzQ/UiIo5P2sD8I5lEO
Xdf9Eicy9y5z2Ci2zrmDcAGWL8o5wOWrCqML2ijximFzyQ/swlMC9xBIX9RCFws=
</X509Certificate>
</X509Data>
</KeyInfo>
<Object Id="prop"><SignatureProperties xmlns:dsp="http://www.w3.org/2009/xmldsig-properties"><SignatureProperty Id="profile" Target="#DistributorSignature"><dsp:Profile URI="http://www.w3.org/ns/widgets-digsig#profile"></dsp:Profile></SignatureProperty><SignatureProperty Id="role" Target="#DistributorSignature"><dsp:Role URI="http://www.w3.org/ns/widgets-digsig#role-distributor"></dsp:Role></SignatureProperty><SignatureProperty Id="identifier" Target="#DistributorSignature"><dsp:Identifier></dsp:Identifier></SignatureProperty></SignatureProperties></Object>
</Signature>